textmidiformeditpackage/AllFormsWindow.py
textmidiformeditpackage/FormFrame.py
textmidiformeditpackage/GeneralMIDI.py
textmidiformeditpackage/KeyboardWindow.py
textmidiformeditpackage/Sine.py
textmidiformeditpackage/VoiceWindow.py
textmidiformeditpackage/__init__.py
textmidiformeditpackage/textmidiformedit.py
textmidiformedit-1.0.69.dist-info/AUTHORS
textmidiformedit-1.0.69.dist-info/COPYING
textmidiformedit-1.0.69.dist-info/LICENSE
textmidiformedit-1.0.69.dist-info/METADATA
textmidiformedit-1.0.69.dist-info/WHEEL
textmidiformedit-1.0.69.dist-info/top_level.txt
textmidiformedit-1.0.69.dist-info/RECORD
