Metadata-Version: 2.1
Name: textmidiformedit
Version: 1.0.69
Summary: A python package for editing forms used by textmidicgm, "Text MIDI Computer-Generated Music".
Home-page: https://github.com/tomejanzen/TextMIDITools
Author: Thomas E. Janzen
Author-email: janzenttome@gmail.com
Project-URL: Bug Tracker, https://github.com/tomejanzen/TetMIDITools/issues
Classifier: Programming Language :: Python :: 3
Classifier: License :: OSI Approved :: MIT License
Classifier: Operating System :: OS Independent
Requires-Python: >=3.9
License-File: LICENSE
License-File: COPYING
License-File: AUTHORS
